{
    "Rank1": {
        "SkillRank": 1,
        "SkillType": "Fire",
        "SkillName": "Fire Alignment I",
        "SkillDescription": "Fire Alignment I",
        "DataClass": "FireAlignment",
        "StatChanges": []
    },
    "Rank2": {
        "SkillRank": 2,
        "SkillType": "Fire",
        "SkillName": "Spellcaster I",
        "SkillDescription": "Spellcaster I",
        "DataClass": "Spellcaster",
        "StatChanges": [
            {
                "RequiredAttackTypesAND": [
                    "SpellFire"
                ],
                "SourceTargetType": "Self",
                "DestinationTargetType": "Self",
                "StatChangeEntries": [
                    {
                        "SourceStatType": "MagicCostDelta",
                        "DestinationStatType": "MagicCostDelta",
                        "ChangeAmount": 1,
                        "OperationType": "Subtract",
                        "AssignmentType": "Set"
                    }
                ]
            }
        ]
    },
    "Rank3": {
        "SkillRank": 3,
        "SkillType": "Fire",
        "SkillName": "Power Player I",
        "SkillDescription": "Power Player I",
        "DataClass": "PowerPlayer",
        "StatChanges": [
            {
                "RequiredAttackTypesAND": [
                    "PowerFire"
                ],
                "SourceTargetType": "Self",
                "DestinationTargetType": "Self",
                "StatChangeEntries": [
                    {
                        "SourceStatType": "EnergyCostDelta",
                        "DestinationStatType": "EnergyCostDelta",
                        "ChangeAmount": 1,
                        "OperationType": "Subtract",
                        "AssignmentType": "Set"
                    }
                ]
            }
        ]
    },
    "Rank4": {
        "SkillRank": 4,
        "SkillType": "Fire",
        "SkillName": "Fire Absorption I",
        "SkillDescription": "Fire Absorption I",
        "DataClass": "FireAbsorption",
        "StatChanges": [
            {
                "RequiredDefendTypesOR": [
                    "SpellFire",
                    "PowerFire"
                ],
                "SourceTargetType": "Self",
                "DestinationTargetType": "Self",
                "StatChangeEntries": [
                    {
                        "SourceStatType": "GeneralDamageBonusValue",
                        "DestinationStatType": "GeneralDamageBonusValue",
                        "ChangeAmount": 1,
                        "OperationType": "Subtract",
                        "AssignmentType": "Set"
                    }
                ]
            }
        ]
    },
    "Rank5": {
        "SkillRank": 5,
        "SkillType": "Fire",
        "SkillName": "Gem Juicer I",
        "SkillDescription": "Gem Juicer I",
        "DataClass": "GemJuicer",
        "StatChanges": [
            {
                "SourceTargetType": "Self",
                "DestinationTargetType": "Self",
                "StatChangeEntries": [
                    {
                        "SourceStatType": "RubyValueDelta",
                        "DestinationStatType": "RubyValueDelta",
                        "ChangeAmount": 1,
                        "OperationType": "Add",
                        "AssignmentType": "Set"
                    }
                ]
            }
        ]
    },
    "Rank6": {
        "SkillRank": 6,
        "SkillType": "Fire",
        "SkillName": "Fire Alignment II",
        "SkillDescription": "Fire Alignment II",
        "DataClass": "FireAlignment",
        "StatChanges": [
            {
                "RequiredAttackTypesOR": [
                    "SpellFire",
                    "PowerFire"
                ],
                "SourceTargetType": "Self",
                "DestinationTargetType": "Self",
                "StatChangeEntries": [
                    {
                        "SourceStatType": "GeneralDamageBonusPercent",
                        "DestinationStatType": "GeneralDamageBonusPercent",
                        "ChangeAmount": 0.05,
                        "OperationType": "Add",
                        "AssignmentType": "Set"
                    }
                ]
            }
        ]
    },
    "Rank7": {
        "SkillRank": 7,
        "SkillType": "Fire",
        "SkillName": "Spellcaster II",
        "SkillDescription": "Spellcaster II",
        "DataClass": "Spellcaster",
        "StatChanges": [
            {
                "RequiredAttackTypesAND": [
                    "SpellFire"
                ],
                "SourceTargetType": "Self",
                "DestinationTargetType": "Self",
                "StatChangeEntries": [
                    {
                        "SourceStatType": "MagicCostDelta",
                        "DestinationStatType": "MagicCostDelta",
                        "ChangeAmount": 2,
                        "OperationType": "Subtract",
                        "AssignmentType": "Set"
                    }
                ]
            }
        ]
    },
    "Rank8": {
        "SkillRank": 8,
        "SkillType": "Fire",
        "SkillName": "Power Player II",
        "SkillDescription": "Power Player II",
        "DataClass": "PowerPlayer",
        "StatChanges": [
            {
                "RequiredAttackTypesAND": [
                    "PowerFire"
                ],
                "SourceTargetType": "Self",
                "DestinationTargetType": "Self",
                "StatChangeEntries": [
                    {
                        "SourceStatType": "EnergyCostDelta",
                        "DestinationStatType": "EnergyCostDelta",
                        "ChangeAmount": 2,
                        "OperationType": "Subtract",
                        "AssignmentType": "Set"
                    }
                ]
            }
        ]
    },
    "Rank9": {
        "SkillRank": 9,
        "SkillType": "Fire",
        "SkillName": "Fire Absorption II",
        "SkillDescription": "Fire Absorption II",
        "DataClass": "FireAbsorption",
        "StatChanges": [
            {
                "RequiredDefendTypesOR": [
                    "SpellFire",
                    "PowerFire"
                ],
                "SourceTargetType": "Self",
                "DestinationTargetType": "Self",
                "StatChangeEntries": [
                    {
                        "SourceStatType": "GeneralDamageBonusValue",
                        "DestinationStatType": "GeneralDamageBonusValue",
                        "ChangeAmount": 2,
                        "OperationType": "Subtract",
                        "AssignmentType": "Set"
                    }
                ]
            }
        ]
    },
    "Rank10": {
        "SkillRank": 10,
        "SkillType": "Fire",
        "SkillName": "Gem Juicer II",
        "SkillDescription": "Gem Juicer II",
        "DataClass": "GemJuicer",
        "StatChanges": [
            {
                "SourceTargetType": "Self",
                "DestinationTargetType": "Self",
                "StatChangeEntries": [
                    {
                        "SourceStatType": "RubyValueDelta",
                        "DestinationStatType": "RubyValueDelta",
                        "ChangeAmount": 2,
                        "OperationType": "Add",
                        "AssignmentType": "Set"
                    }
                ]
            }
        ]
    },
    "Rank11": {
        "SkillRank": 11,
        "SkillType": "Fire",
        "SkillName": "Fire Alignment III",
        "SkillDescription": "Fire Alignment III",
        "DataClass": "FireAlignment",
        "StatChanges": [
            {
                "RequiredAttackTypesOR": [
                    "SpellFire",
                    "PowerFire"
                ],
                "SourceTargetType": "Self",
                "DestinationTargetType": "Self",
                "StatChangeEntries": [
                    {
                        "SourceStatType": "GeneralDamageBonusPercent",
                        "DestinationStatType": "GeneralDamageBonusPercent",
                        "ChangeAmount": 0.1,
                        "OperationType": "Add",
                        "AssignmentType": "Set"
                    }
                ]
            }
        ]
    },
    "Rank12": {
        "SkillRank": 12,
        "SkillType": "Fire",
        "SkillName": "Spellcaster III",
        "SkillDescription": "Spellcaster III",
        "DataClass": "Spellcaster",
        "StatChanges": [
            {
                "RequiredAttackTypesAND": [
                    "SpellFire"
                ],
                "SourceTargetType": "Self",
                "DestinationTargetType": "Self",
                "StatChangeEntries": [
                    {
                        "SourceStatType": "MagicCostDelta",
                        "DestinationStatType": "MagicCostDelta",
                        "ChangeAmount": 3,
                        "OperationType": "Subtract",
                        "AssignmentType": "Set"
                    }
                ]
            }
        ]
    },
    "Rank13": {
        "SkillRank": 13,
        "SkillType": "Fire",
        "SkillName": "Power Player III",
        "SkillDescription": "Power Player III",
        "DataClass": "PowerPlayer",
        "StatChanges": [
            {
                "RequiredAttackTypesAND": [
                    "PowerFire"
                ],
                "SourceTargetType": "Self",
                "DestinationTargetType": "Self",
                "StatChangeEntries": [
                    {
                        "SourceStatType": "EnergyCostDelta",
                        "DestinationStatType": "EnergyCostDelta",
                        "ChangeAmount": 3,
                        "OperationType": "Subtract",
                        "AssignmentType": "Set"
                    }
                ]
            }
        ]
    },
    "Rank14": {
        "SkillRank": 14,
        "SkillType": "Fire",
        "SkillName": "Fire Absorption III",
        "SkillDescription": "Fire Absorption III",
        "DataClass": "FireAbsorption",
        "StatChanges": [
            {
                "RequiredDefendTypesOR": [
                    "SpellFire",
                    "PowerFire"
                ],
                "SourceTargetType": "Self",
                "DestinationTargetType": "Self",
                "StatChangeEntries": [
                    {
                        "SourceStatType": "GeneralDamageBonusValue",
                        "DestinationStatType": "GeneralDamageBonusValue",
                        "ChangeAmount": 3,
                        "OperationType": "Subtract",
                        "AssignmentType": "Set"
                    }
                ]
            }
        ]
    },
    "Rank15": {
        "SkillRank": 15,
        "SkillType": "Fire",
        "SkillName": "Gem Juicer III",
        "SkillDescription": "Gem Juicer III",
        "DataClass": "GemJuicer",
        "StatChanges": [
            {
                "SourceTargetType": "Self",
                "DestinationTargetType": "Self",
                "StatChangeEntries": [
                    {
                        "SourceStatType": "RubyValueDelta",
                        "DestinationStatType": "RubyValueDelta",
                        "ChangeAmount": 3,
                        "OperationType": "Add",
                        "AssignmentType": "Set"
                    }
                ]
            }
        ]
    },
    "Rank16": {
        "SkillRank": 16,
        "SkillType": "Fire",
        "SkillName": "Fire Alignment IV",
        "SkillDescription": "Fire Alignment IV",
        "DataClass": "FireAlignment",
        "StatChanges": [
            {
                "RequiredAttackTypesOR": [
                    "SpellFire",
                    "PowerFire"
                ],
                "SourceTargetType": "Self",
                "DestinationTargetType": "Self",
                "StatChangeEntries": [
                    {
                        "SourceStatType": "GeneralDamageBonusPercent",
                        "DestinationStatType": "GeneralDamageBonusPercent",
                        "ChangeAmount": 0.15,
                        "OperationType": "Add",
                        "AssignmentType": "Set"
                    }
                ]
            }
        ]
    },
    "Rank17": {
        "SkillRank": 17,
        "SkillType": "Fire",
        "SkillName": "Spellcaster IV",
        "SkillDescription": "Spellcaster IV",
        "DataClass": "Spellcaster",
        "StatChanges": [
            {
                "RequiredAttackTypesAND": [
                    "SpellFire"
                ],
                "SourceTargetType": "Self",
                "DestinationTargetType": "Self",
                "StatChangeEntries": [
                    {
                        "SourceStatType": "MagicCostDelta",
                        "DestinationStatType": "MagicCostDelta",
                        "ChangeAmount": 4,
                        "OperationType": "Subtract",
                        "AssignmentType": "Set"
                    }
                ]
            }
        ]
    },
    "Rank18": {
        "SkillRank": 18,
        "SkillType": "Fire",
        "SkillName": "Power Player IV",
        "SkillDescription": "Power Player IV",
        "DataClass": "PowerPlayer",
        "StatChanges": [
            {
                "RequiredAttackTypesAND": [
                    "PowerFire"
                ],
                "SourceTargetType": "Self",
                "DestinationTargetType": "Self",
                "StatChangeEntries": [
                    {
                        "SourceStatType": "EnergyCostDelta",
                        "DestinationStatType": "EnergyCostDelta",
                        "ChangeAmount": 4,
                        "OperationType": "Subtract",
                        "AssignmentType": "Set"
                    }
                ]
            }
        ]
    },
    "Rank19": {
        "SkillRank": 19,
        "SkillType": "Fire",
        "SkillName": "Fire Absorption IV",
        "SkillDescription": "Fire Absorption IV",
        "DataClass": "FireAbsorption",
        "StatChanges": [
            {
                "RequiredDefendTypesOR": [
                    "SpellFire",
                    "PowerFire"
                ],
                "SourceTargetType": "Self",
                "DestinationTargetType": "Self",
                "StatChangeEntries": [
                    {
                        "SourceStatType": "GeneralDamageBonusValue",
                        "DestinationStatType": "GeneralDamageBonusValue",
                        "ChangeAmount": 4,
                        "OperationType": "Subtract",
                        "AssignmentType": "Set"
                    }
                ]
            }
        ]
    },
    "Rank20": {
        "SkillRank": 20,
        "SkillType": "Fire",
        "SkillName": "Gem Juicer IV",
        "SkillDescription": "Gem Juicer IV",
        "DataClass": "GemJuicer",
        "StatChanges": [
            {
                "SourceTargetType": "Self",
                "DestinationTargetType": "Self",
                "StatChangeEntries": [
                    {
                        "SourceStatType": "RubyValueDelta",
                        "DestinationStatType": "RubyValueDelta",
                        "ChangeAmount": 4,
                        "OperationType": "Add",
                        "AssignmentType": "Set"
                    }
                ]
            }
        ]
    }
}
