{
    "Rank1": {
        "SkillRank": 1,
        "SkillType": "Goldsmith",
        "SkillName": "Recipe I",
        "SkillDescription": "4x Bronze Sheets (1x Bronze Bar)",
        "DataClass": "RecipeI",
        "Recipes": [],
        "StatChanges": []
    },
    "Rank2": {
        "SkillRank": 2,
        "SkillType": "Goldsmith",
        "SkillName": "Recipe II",
        "SkillDescription": "Bronze Ring (1x Bronze Sheet)",
        "DataClass": "RecipeII",
        "Recipes": [],
        "StatChanges": []
    },
    "Rank3": {
        "SkillRank": 3,
        "SkillType": "Goldsmith",
        "SkillName": "Recipe III",
        "SkillDescription": "Peasant Bronze Ring (2x Bronze Sheets)",
        "DataClass": "RecipeIII",
        "Recipes": [],
        "StatChanges": []
    },
    "Rank4": {
        "SkillRank": 4,
        "SkillType": "Goldsmith",
        "SkillName": "Recipe IV",
        "SkillDescription": "Merchant Bronze Ring (3x Bronze Sheets)",
        "DataClass": "RecipeIV",
        "Recipes": [],
        "StatChanges": []
    },
    "Rank5": {
        "SkillRank": 5,
        "SkillType": "Goldsmith",
        "SkillName": "Recipe V",
        "SkillDescription": "Lady Bronze Ring (4x Bronze Sheets)",
        "DataClass": "RecipeV",
        "Recipes": [],
        "StatChanges": []
    },
    "Rank6": {
        "SkillRank": 6,
        "SkillType": "Goldsmith",
        "SkillName": "Recipe VI",
        "SkillDescription": "Bronze Amulet (2x Bronze Sheets)",
        "DataClass": "RecipeVI",
        "Recipes": [],
        "StatChanges": []
    },
    "Rank7": {
        "SkillRank": 7,
        "SkillType": "Goldsmith",
        "SkillName": "Recipe VII",
        "SkillDescription": "Peasant Bronze Amulet (4x Bronze Sheets)",
        "DataClass": "RecipeVII",
        "Recipes": [],
        "StatChanges": []
    },
    "Rank8": {
        "SkillRank": 8,
        "SkillType": "Goldsmith",
        "SkillName": "Recipe VIII",
        "SkillDescription": "Merchant Bronze Amulet (6x Bronze Sheets)",
        "DataClass": "RecipeVIII",
        "Recipes": [],
        "StatChanges": []
    },
    "Rank9": {
        "SkillRank": 9,
        "SkillType": "Goldsmith",
        "SkillName": "Recipe IX",
        "SkillDescription": "Lady Bronze Amulet (8x Bronze Sheets)",
        "DataClass": "RecipeIX",
        "Recipes": [],
        "StatChanges": []
    },
    "Rank10": {
        "SkillRank": 10,
        "SkillType": "Goldsmith",
        "SkillName": "Gem Mastery I",
        "SkillDescription": "Able to Add/Remove Gems from Recipes III-IX",
        "DataClass": "GemMastery",
        "Recipes": [],
        "StatChanges": []
    },
    "Rank11": {
        "SkillRank": 11,
        "SkillType": "Goldsmith",
        "SkillName": "Recipe X",
        "SkillDescription": "4x Iron Sheets (1x Iron Bar)",
        "DataClass": "RecipeX",
        "Recipes": [],
        "StatChanges": []
    },
    "Rank12": {
        "SkillRank": 12,
        "SkillType": "Goldsmith",
        "SkillName": "Recipe XI",
        "SkillDescription": "Iron Ring (1x Iron Sheet)",
        "DataClass": "RecipeXI",
        "Recipes": [],
        "StatChanges": []
    },
    "Rank13": {
        "SkillRank": 13,
        "SkillType": "Goldsmith",
        "SkillName": "Recipe XII",
        "SkillDescription": "Peasant Iron Ring (2x Iron Sheets)",
        "DataClass": "RecipeXII",
        "Recipes": [],
        "StatChanges": []
    },
    "Rank14": {
        "SkillRank": 14,
        "SkillType": "Goldsmith",
        "SkillName": "Recipe XIII",
        "SkillDescription": "Merchant Iron Ring (3x Iron Sheets)",
        "DataClass": "RecipeXIII",
        "Recipes": [],
        "StatChanges": []
    },
    "Rank15": {
        "SkillRank": 15,
        "SkillType": "Goldsmith",
        "SkillName": "Recipe XIV",
        "SkillDescription": "Lady Iron Ring (4x Iron Sheets)",
        "DataClass": "RecipeXIV",
        "Recipes": [],
        "StatChanges": []
    },
    "Rank16": {
        "SkillRank": 16,
        "SkillType": "Goldsmith",
        "SkillName": "Recipe XV",
        "SkillDescription": "Iron Amulet (2x Iron Sheets)",
        "DataClass": "RecipeXV",
        "Recipes": [],
        "StatChanges": []
    },
    "Rank17": {
        "SkillRank": 17,
        "SkillType": "Goldsmith",
        "SkillName": "Recipe XVI",
        "SkillDescription": "Peasant Iron Amulet (4x Iron Sheets)",
        "DataClass": "RecipeXVI",
        "Recipes": [],
        "StatChanges": []
    },
    "Rank18": {
        "SkillRank": 18,
        "SkillType": "Goldsmith",
        "SkillName": "Recipe XVII",
        "SkillDescription": "Merchant Iron Amulet (6x Iron Sheets)",
        "DataClass": "RecipeXVII",
        "Recipes": [],
        "StatChanges": []
    },
    "Rank19": {
        "SkillRank": 19,
        "SkillType": "Goldsmith",
        "SkillName": "Recipe XVIII",
        "SkillDescription": "Lady Iron Amulet (8x Iron Sheets)",
        "DataClass": "RecipeXVIII",
        "Recipes": [],
        "StatChanges": []
    },
    "Rank20": {
        "SkillRank": 20,
        "SkillType": "Goldsmith",
        "SkillName": "Gem Mastery II",
        "SkillDescription": "Able to Add/Remove Gems from Recipes X-XVIII",
        "DataClass": "GemMastery",
        "Recipes": [],
        "StatChanges": []
    }
}
